{
 "公孫勝": [
  "與喬道清一同領兵前往汾陽，試圖勸降馬靈。"
 ],
 "凌振": [
  "隨宋江離開昭德，前往北進發。"
 ],
 "劉唐": [
  "隨宋江離開昭德，前往北進發。"
 ],
 "吳用": [
  "與宋江商議分撥將佐迎敵鄔梨與瓊英。",
  "識破葉清來意，向宋江獻計利用張清與瓊英的姻緣作為內應。",
  "派遣李逵、武松保護蕭讓前往襄垣，搜覓鄔梨筆跡以假造書札。"
 ],
 "單廷珪": [
  "受宋江命令，與索超、徐寧等人統領軍馬攻取潞城縣。"
 ],
 "孫新": [
  "與王英、扈三娘、顧大嫂領兵哨探北軍虛實。",
  "在戰鬥中雙出死救被瓊英擊落的丈夫王英。",
  "舞雙鞭搶戰瓊英，頭盔被石子擊中後急回本陣。"
 ],
 "孫立": [
  "被宋江薦舉鎮守壺關、抱犢，以替換孫立、朱仝等將佐前來聽用。"
 ],
 "安道全": [
  "隨宋江離開昭德，前往北進發。",
  "為受傷的王英敷治腳傷與頭面破損。",
  "為受傷的林沖進行療治。",
  "向宋江指出張清之病與瓊英之事相符，是姻緣天湊。",
  "假扮醫士全靈，進入襄垣城為鄔梨療治藥箭。",
  "治癒鄔梨後，推薦假扮全羽的張清給鄔梨。",
  "假扮醫士全羽，與瓊英成婚並裏應外合鴆死鄔梨。",
  "與葉清步下軍卒出城到昭德，報知宋先鋒襄垣已破。"
 ],
 "宋江": [
  "引眾將出郭迎接陳安撫，並將其迎入昭德府內歇下。",
  "拜謝陳安撫的賞賜，並表示願肝腦塗地以報恩。",
  "差戴宗往各府州縣傳令，俟新官一到即行交代。",
  "薦舉金鼎、黃鉞鎮守壺關、抱犢，更替孫立、朱仝等將佐。",
  "傳令索超、徐寧等人攻取潞城縣，令王英等人哨探北軍。",
  "統領大軍離開昭德，望北進發。",
  "在陣前聽報瓊英飛石傷人，驚異並派張清接應。",
  "令安道全看治王英，並憂悶解珍、解寶及李逵等人的下落。",
  "釋放被俘的葉清，聽取其關於瓊身世與報仇之志的密報。",
  "依允吳用之計，密語張清、安道全、葉清受計。",
  "聞報索超等攻克潞城，大喜並標錄功次賞賜。"
 ],
 "宋清": [
  "隨宋江離開昭德，前往北進發。"
 ],
 "張清": [
  "隨宋江離開昭德，前往北進發。",
  "聽報瓊英飛石傷人後，披掛上馬領軍接應，欲認那女先鋒。",
  "被吳用計策選中，假扮醫士全羽之弟全羽，進入襄垣城。",
  "在演武廳與瓊英比試武藝，並接住瓊英飛來的石子。",
  "與瓊英石子對打，打得雪片般落下，令瓊英驚異。",
  "被鄔梨賜衣甲馬匹，領兵出城迎敵並殺退宋兵。",
  "再次領兵出城迎敵，用石子打得宋將亂竄奔逃。",
  "被鄔梨招贅為婿，與瓊英成婚。",
  "在洞房中向瓊英說出真姓名，並與瓊英裏應外合鴆死鄔梨。",
  "下令城中嚴禁走透消息，並放出解珍、解寶分守四門。"
 ],
 "徐寧": [
  "隨宋江離開昭德，前往北進發。",
  "受宋江命令，與索超等人攻取潞城縣。",
  "設計令軍士裸形大罵，激怒潞城軍士出戰。",
  "搠翻北將池方，奪取潞城城池。"
 ],
 "戴宗": [
  "受宋江差遣，往各府州縣鎮守頭領處傳令。",
  "往邠陽探聽軍情回報。"
 ],
 "扈三娘": [
  "與王英、孫新、顧大嫂領騎兵先行哨探北軍虛實。",
  "在戰鬥中助丈夫王英廝殺，砍翻北將盛本。",
  "見丈夫王英被瓊英刺傷，飛馬搶出救夫。",
  "與瓊英廝殺二十餘合，被瓊英飛石子打中右手腕，撇刀回陣。"
 ],
 "朱仝": [
  "被宋江薦舉鎮守壺關、抱犢，以替換孫立、朱仝等將佐前來聽用。"
 ],
 "朱貴": [
  "隨宋江離開昭德，前往北進發。",
  "受宋江差遣，分四路尋覓失蹤的魯智深。"
 ],
 "李袞": [
  "隨宋江離開昭德，前往北進發。",
  "奉宋公明將令，領軍接應林沖等人。"
 ],
 "李逵": [
  "隨宋江離開昭德，前往北進發。",
  "奉宋公明將令，領軍接應林沖等人。",
  "衝入北陣，被瓊英飛石子打中額角，鮮血迸流。",
  "再次被瓊英飛石子打中額角，仍揮雙斧撞入陣中亂砍。",
  "殺得滿身血污，與武松一同沖透北軍回寨。",
  "受吳用命令，黑夜裏保護蕭讓到襄垣相見瓊英、張清。"
 ],
 "林沖": [
  "隨宋江離開昭德，前往北進發。",
  "奉宋公明將令，領軍接應王英等人。",
  "與瓊英廝鬥，被瓊英飛石子打中臉上，鮮血迸流，拖矛回陣。"
 ],
 "樂和": [
  "隨宋江離開昭德，前往北進發。",
  "受宋江差遣，分四路尋覓失蹤的魯智深。"
 ],
 "樊瑞": [
  "隨宋江離開昭德，前往北進發。"
 ],
 "武松": [
  "隨宋江離開昭德，前往北進發。",
  "奉宋公明將令，領軍接應林沖等人。",
  "衝入北陣，與李逵一同殺條血路沖透北軍。",
  "與李逵殺死軍士，奪回解珍、解寶，但復被奪去。",
  "與李逵殺開一條路空手回寨，並告知宋江魯智深失蹤。",
  "受吳用命令，黑夜裏保護蕭讓到襄垣相見瓊英、張清。"
 ],
 "段景住": [
  "隨宋江離開昭德，前往北進發。",
  "受宋江差遣，分四路尋覓失蹤的魯智深。"
 ],
 "湯隆": [
  "受宋江命令，與索超、徐寧等人攻取潞城縣。",
  "從西路引兵撞入潞城，與唐斌配合奪取城池。"
 ],
 "王英": [
  "受宋江命令，與扈三娘等人領兵哨探北軍虛實。",
  "與北將盛本廝殺十數合，後與扈三娘合力擊退盛本。",
  "見瓊英美貌，驟馬出陣搶戰，鎗法大亂。",
  "被瓊英一戟刺中左腿，撞下馬來。"
 ],
 "瓊英": [
  "被鄔梨奏過田虎，封為先鋒，統領五千精兵進征。",
  "擊碎臥房脊上鴟尾，展示飛石子異術。",
  "與王英廝殺十數餘合，刺中王英左腿。",
  "與扈三娘、顧大嫂廝殺二十餘合，飛石子打中扈三娘右手腕。",
  "飛石子打中孫新頭盔，孫新驚退。",
  "與林沖廝鬥，賣破綻後飛石子打中林沖臉上。",
  "飛石子打中李逵額角兩次，並打翻解珍。",
  "保護中箭的鄔梨，轉過長林望襄垣而去。",
  "在演武廳與全羽（張清）比試武藝，並飛石子與全羽對打。",
  "被葉清攛掇，與全羽（張清）成婚。",
  "在洞房中向張清訴說冤苦，並與其裏應外合鴆死鄔梨。",
  "下令嚴禁走透消息，並放出解珍、解寶分守四門。"
 ],
 "田虎": [
  "派遣鄔梨分兵摽掠，擄掠瓊英等人。",
  "派遣馬靈救汾陽，派遣鄔梨同瓊英從東殺至襄垣。",
  "封鄔梨為國舅，瓊英為郡主。",
  "聽聞喬道清、孫安降服及昭德、潞城已破，大驚。",
  "接見葉清賫領的鄔梨書札。"
 ],
 "皇甫端": [
  "隨宋江離開昭德，前往北進發。"
 ],
 "索超": [
  "受宋江命令，與徐寧等人攻取潞城縣。",
  "圍攻潞城，待北軍出戰後，與眾將入城安撫百姓。",
  "攻克潞城後，差人來報捷音。"
 ],
 "蔡慶": [
  "隨宋江離開昭德，前往北進發。"
 ],
 "蔡福": [
  "隨宋江離開昭德，前往北進發。"
 ],
 "蔣敬": [
  "隨宋江離開昭德，前往北進發。"
 ],
 "蕭讓": [
  "隨宋江離開昭德，前往北進發。",
  "受吳用命令，由李逵、武松保護，黑夜裏到襄垣相見瓊英、張清。",
  "搜覓鄔梨筆跡，假寫鄔梨字樣申文書札。"
 ],
 "裴宣": [
  "隨宋江離開昭德，前往北進發。"
 ],
 "解寶": [
  "隨宋江離開昭德，前往北進發。",
  "奉宋公明將令，領軍接應林沖等人。",
  "被北軍撒起絆索，橫拖倒拽，捉入陣中。",
  "被徐威等軍士綁縛，欲進城去。",
  "被武松、李逵殺死軍士奪回，但復被徐威等大軍趕來奪去。",
  "被解珍扶著，不便廝殺，被北軍趕上捉入陣中。",
  "被張清、瓊英下令放出，同張清、葉清分守四門。"
 ],
 "解珍": [
  "隨宋江離開昭德，前往北進發。",
  "奉宋公明將令，領軍接應林沖等人。",
  "被瓊英飛石子打翻在地。",
  "被北軍撒起絆索，橫拖倒拽，捉入陣中。",
  "被徐威等軍士綁縛，欲進城去。",
  "被武松、李逵殺死軍士奪回，但復被徐威等大軍趕來奪去。",
  "被解寶扶著，不便廝殺，被北軍趕上捉入陣中。",
  "被張清、瓊英下令放出，同張清、葉清分守四門。"
 ],
 "郁保四": [
  "隨宋江離開昭德，前往北進發。",
  "獲得奸細一名，解進寨來，該奸細為北將總管葉清。",
  "受宋江差遣，分四路尋覓失蹤的魯智深。"
 ],
 "鄔梨": [
  "令郡主瓊英為先鋒，自己統領大軍隨後進征。",
  "見瓊英飛石子百發百中，大驚並終日教導其武藝。",
  "萌生異心，保奏瓊英做先鋒，欲乘兩家爭鬥於中取事。",
  "在陣上被孫安手下軍卒放冷箭射中脖項，翻身落馬。",
  "被醫士全靈（安道全）療治，五日後飲食復舊。",
  "賜全羽（張清）衣甲馬匹，令其領兵出城迎敵。",
  "聽從葉清建議，招贅全羽（張清）為婿。",
  "被張清、瓊英裏應外合鴆死。"
 ],
 "金大堅": [
  "隨宋江離開昭德，前往北進發。"
 ],
 "項充": [
  "隨宋江離開昭德，前往北進發。",
  "奉宋公明將令，領軍接應林沖等人。"
 ],
 "顧大嫂": [
  "與王英、扈三娘、孫新領騎兵先行哨探北軍虛實。",
  "見扈三娘鬥瓊英不過，使雙刀拍馬上前助戰。",
  "見扈三娘被石子打中，撇了瓊英，來救扈三娘。"
 ],
 "魏定國": [
  "受宋江命令，與索超、徐寧等人攻取潞城縣。"
 ],
 "魯智深": [
  "隨宋江離開昭德，前往北進發。",
  "奉宋公明將令，領軍接應林沖等人。",
  "衝入北陣，恐李逵有失，一齊衝殺過來。",
  "與武松、解寶救了解珍，翻身殺入北陣。",
  "殺入陣後失蹤，宋江差人四下跟尋探聽其蹤跡。"
 ]
}