{
 "劉唐": [
  "劉唐與魯智深、武松齊聲大叫並奮力回身向北殺來，隨後被金甲神人打翻並被北軍活捉。",
  "劉唐被喬道清監禁，並與魯智深、武松等人齊聲罵喬道清是妖道。"
 ],
 "吳用": [
  "吳用勸宋江速往壺關取樊瑞抵敵，並苦諫宋江不要親自進兵。",
  "吳用統領眾將守寨，後領兵接應宋江。",
  "吳用解釋位尊戊己者是土神，因宋江忠義感動后土之神，土能剋水，故妖水得解。",
  "吳用建議宋江傳令大兵退十里另紮營寨，並分紮營寨如六花陣之法以防劫寨。",
  "吳用建議按兵不動，待公孫勝到來再作計較。",
  "吳用令張清、王英、解珍、解寶領輕騎馳往衛州接取公孫勝。"
 ],
 "單廷珪": [
  "單廷珪領五百步兵，盡是黑旗黑甲，手執團牌標鎗、鋼叉利刃，與魏定國一同衝殺北軍。",
  "單廷珪被喬道清降下的冰雹打得星落雲散，嚇得魂不附體並抵死逃回本陣。"
 ],
 "孫新": [
  "孫新與吳用、王英、扈三娘、解珍、解寶領兵一萬前來接應宋江。"
 ],
 "宋江": [
  "宋江聞李逵等被擒大驚哭泣，並親自統領八員將佐及二萬軍馬殺向昭德城南。",
  "宋江出馬指著喬道清罵道，要求放還兄弟及五百餘人，否則拿住他碎屍萬段。",
  "宋江在喬道清妖術下被衝動，急回馬擁護宋江望北奔走，後在困境中仰天歎道願死以免被擒受辱。",
  "宋江被土神救脫後，對吳用表示不聽賢弟之言險些不得相見。",
  "宋江計點軍士損折萬餘，並傳令大兵退十里另紮營寨。",
  "宋江令樊瑞、單廷珪、魏定國整點軍兵準備迎敵。",
  "宋江在喬道清與樊瑞鬥法時，見樊瑞法術不靈抵擋不住，處於萬分危急之中。"
 ],
 "張清": [
  "張清與索超合兵一處，殺奔城下來。",
  "張清與宋江等七個頭領擁護宋江團聚一塊，並道願隨兄長為厲鬼殺賊。",
  "張清領輕騎五百，星夜出關馳往衛州，接取公孫勝。"
 ],
 "徐寧": [
  "徐寧與林沖在東門聽得城南喊殺連天，急領兵來接應。",
  "徐寧同耿恭投大寨，並急同耿恭投大寨來。",
  "徐寧與林沖等七個頭領擁護宋江團聚一塊，並道願隨兄長為厲鬼殺賊。"
 ],
 "扈三娘": [
  "扈三娘與王英領三百騎哨到，得知耿恭消息後一同來報知宋先鋒。",
  "扈三娘與吳用、孫新、解珍、解寶領兵一萬前來接應宋江。"
 ],
 "李袞": [
  "李袞被喬道清生擒活捉，並被軍士綁縛解到帳前。",
  "李袞被喬道清監禁。"
 ],
 "李逵": [
  "李逵不聽唐斌、耿恭說話，領眾將殺過陣去，被喬道清使妖術困住並被生擒活捉。",
  "李逵被喬道清監禁，並睜圓怪眼、倒豎虎鬚、挺胸大罵喬道清。",
  "李逵大叫如雷，表示若皺眉就不算好漢，並被喬道清下令監禁聽候。"
 ],
 "林沖": [
  "林沖與徐寧在東門聽得城南喊殺連天，急領兵來接應。",
  "林沖同耿恭投大寨，並急同耿恭投大寨來。",
  "林沖與徐寧等七個頭領擁護宋江團聚一塊，並道願隨兄長為厲鬼殺賊。",
  "林沖在喬道清妖術下急回馬擁護宋江望北奔走。"
 ],
 "樊瑞": [
  "樊瑞奉令從壺關馳到，入寨參見宋江，並表示明日作法擒喬道清。",
  "樊瑞手仗寶劍出陣，指著喬道清大罵並與其比武藝。",
  "樊瑞與喬道清兩劍並舉廝殺，後各運神通，因喬道清使烏龍蛻骨之法而惶恐歸陣。",
  "樊瑞羞忿交集，披髮仗劍使盡平生法力念動咒語，招動人馬衝殺過來，但因風砂被喬道清反制而回馬便走。",
  "樊瑞法術不靈，抵擋不住喬道清的追趕。"
 ],
 "武松": [
  "武松與魯智深、劉唐齊聲大叫並奮力回身向北殺來，隨後被金甲神人打翻並被北軍活捉。",
  "武松被喬道清監禁，並與魯智深、劉唐等齊聲罵喬道清是妖道。",
  "武松罵喬道清是腌臢反賊，要求早早把俺砍了乾淨。"
 ],
 "湯隆": [
  "湯隆與宋江等七個頭領擁護宋江團聚一塊，並道願隨兄長為厲鬼殺賊。"
 ],
 "王英": [
  "王英與扈三娘領三百騎哨到，得知耿恭消息後一同來報知宋先鋒。",
  "王英與吳用、孫新、解珍、解寶領兵一萬前來接應宋江。",
  "王英領輕騎五百，星夜出關馳往衛州，接取公孫勝。"
 ],
 "索超": [
  "索超與張清合兵一處，搖旗擂鼓，吶喊篩鑼，殺奔城下來。",
  "索超與林沖等七個頭領擁護宋江團聚一塊，並道願隨兄長為厲鬼殺賊。"
 ],
 "解寶": [
  "解寶與吳用、王英、扈三娘、孫新、解珍領兵一萬前來接應宋江。",
  "解寶領輕騎五百，星夜出關馳往衛州，接取公孫勝。"
 ],
 "解珍": [
  "解寶與吳用、王英、扈三娘、孫新、解珍領兵一萬前來接應宋江。",
  "解寶領輕騎五百，星夜出關馳往衛州，接取公孫勝。"
 ],
 "郁保四": [
  "郁保四捧著帥字旗，立於宋江馬前。",
  "郁保四在窘迫慌亂的地位，身上中了兩矢，仍挺挺捧著帥字旗，緊緊跟隨宋先鋒，不離尺寸。"
 ],
 "項充": [
  "項充被喬道清生擒活捉，並被軍士綁縛解到帳前。",
  "項充被喬道清監禁。"
 ],
 "顧大嫂": [
  "顧大嫂與吳用、王英、扈三娘、孫新、解珍、解寶領兵一萬前來接應宋江。"
 ],
 "魏定國": [
  "魏定國領五百火軍，身穿絳衣，手執火器，前後擁出五十輛火車，與單廷珪一同衝殺北軍。",
  "魏定國被喬道清降下的冰雹打得頭損額破，嚇得魂不附體並舉手無措抵死逃回本陣。"
 ],
 "魯智深": [
  "魯智深與武松、劉唐齊聲大叫並奮力回身向北殺來，隨後被金甲神人打翻並被北軍活捉。",
  "魯智深被喬道清監禁，並呵呵大笑表示視死如歸，今日死得正路。",
  "魯智深與武松、劉唐等齊聲罵喬道清是妖道。"
 ]
}